cv2_extras/__init__.py
cv2_extras/color.py
cv2_extras/utils.py
cv2_extras-0.5.4.dist-info/LICENSE
cv2_extras-0.5.4.dist-info/METADATA
cv2_extras-0.5.4.dist-info/WHEEL
cv2_extras-0.5.4.dist-info/top_level.txt
cv2_extras-0.5.4.dist-info/RECORD
