Metadata-Version: 1.0
Name: cv2_extras
Version: 0.5.4
Summary: A Python library for higher level OpenCV functions used in image analysis and computer vision
Home-page: UNKNOWN
Author: Scott White
Author-email: UNKNOWN
License: BSD 2-Clause License
Platform: UNKNOWN
